rpatoolkit/__init__.py
rpatoolkit/df/__init__.py
rpatoolkit/df/normalize_columns.py
rpatoolkit/df/utils.py
rpatoolkit/fs/__init__.py
rpatoolkit/fs/make_unique_dir.py
rpatoolkit/utils/__init__.py
rpatoolkit/utils/random_string.py
rpatoolkit/utils/strip_punctuation.py
rpatoolkit/xl/__init__.py
rpatoolkit/xl/convert_to_html.py
rpatoolkit/xl/format.py
rpatoolkit/xl/helpers.py
rpatoolkit/xl/read_multiple_sheets.py
rpatoolkit/xl/read_sheet.py
rpatoolkit-0.2.6.dist-info/licenses/LICENSE
rpatoolkit-0.2.6.dist-info/WHEEL
rpatoolkit-0.2.6.dist-info/METADATA
rpatoolkit-0.2.6.dist-info/RECORD
