Metadata-Version: 2.4
Name: rpatoolkit
Version: 0.2.6
Summary: A Python toolkit for Robotic Process Automation (RPA) and ETL pipelines providing solutions to common automation challenges.
Author: fnxL
Author-email: fnxL <ajaykanki.2e@gmail.com>
License-Expression: MIT
License-File: LICENSE
Requires-Dist: fastexcel>=0.18.0
Requires-Dist: openpyxl>=3.1.5
Requires-Dist: polars>=1.36.1
Requires-Dist: python-calamine>=0.6.1
Requires-Dist: xlsx2html>=0.6.2
Requires-Dist: xlsxwriter>=3.2.9
Requires-Python: >=3.10
Project-URL: Homepage, https://github.com/fnxL/rpatoolkit
Project-URL: Issues, https://github.com/fnxL/rpatoolkit/issues
